flask_allows/__init__.py
flask_allows/additional.py
flask_allows/allows.py
flask_allows/overrides.py
flask_allows/permission.py
flask_allows/requirements.py
flask_allows/views.py
flask_allows-0.7.1.dist-info/AUTHORS
flask_allows-0.7.1.dist-info/LICENSE
flask_allows-0.7.1.dist-info/METADATA
flask_allows-0.7.1.dist-info/NOTICE
flask_allows-0.7.1.dist-info/WHEEL
flask_allows-0.7.1.dist-info/top_level.txt
flask_allows-0.7.1.dist-info/RECORD
